{"tileId":"4_34","bounds":{"minX":2000,"maxX":2500,"minZ":17000,"maxZ":17500},"roads":[{"id":"5676412","klass":"residential","bridge":false,"path":[[2284.1,18201.5],[2141.1,17207]],"mid":[2141.1,17207]},{"id":"379499852","klass":"residential","bridge":false,"path":[[1672.2,17546.5],[2451,17433.2]],"mid":[2451,17433.2]},{"id":"379499854","klass":"residential","bridge":false,"path":[[1634.2,17280.4],[2413,17167.6]],"mid":[2413,17167.6]},{"id":"5678179","klass":"residential","bridge":false,"path":[[1947.4,17315.2],[2020.9,17306.1]],"mid":[2020.9,17306.1]},{"id":"421113746","klass":"secondary","bridge":false,"path":[[2028.5,17436.7],[2031.9,17494.2]],"mid":[2031.9,17494.2]},{"id":"421113753","klass":"secondary","bridge":false,"path":[[2019.3,17280.3],[2020.9,17306.1]],"mid":[2020.9,17306.1]},{"id":"733751177","klass":"secondary","bridge":false,"path":[[2024.6,17370.7],[2028.5,17436.7]],"mid":[2028.5,17436.7]},{"id":"736651335","klass":"secondary","bridge":false,"path":[[2020.9,17306.1],[2024.6,17370.7]],"mid":[2024.6,17370.7]},{"id":"1073245780","klass":"residential","bridge":false,"path":[[2451,17433.2],[2467.6,17430.8]],"mid":[2467.6,17430.8]},{"id":"421113751","klass":"secondary","bridge":false,"path":[[2016.2,17225.1],[2019.3,17280.3]],"mid":[2019.3,17280.3]},{"id":"1250689295","klass":"residential","bridge":false,"path":[[2449.6,17689.3],[2375.2,17173]],"mid":[2375.2,17173]},{"id":"421113743","klass":"secondary","bridge":false,"path":[[2002.8,16997.2],[2005.4,17040.9]],"mid":[2005.4,17040.9]},{"id":"421113744","klass":"secondary","bridge":false,"path":[[2007.1,17071.7],[2012.7,17168.4]],"mid":[2012.7,17168.4]},{"id":"421113747","klass":"secondary","bridge":false,"path":[[2012.7,17168.4],[2016.2,17225.1]],"mid":[2016.2,17225.1]},{"id":"421113750","klass":"secondary","bridge":false,"path":[[2005.4,17040.9],[2007.1,17071.7]],"mid":[2007.1,17071.7]},{"id":"441452431","klass":"residential","bridge":false,"path":[[2338.3,16914.7],[2353.7,17023]],"mid":[2353.7,17023]},{"id":"208795706","klass":"residential","bridge":false,"path":[[2416.3,16903.3],[2432.2,17015.9]],"mid":[2432.2,17015.9]},{"id":"1073246843","klass":"residential","bridge":false,"path":[[2413,17167.6],[2429.6,17165.1]],"mid":[2429.6,17165.1]}],"bridges":[]}