{"tileId":"-2_41","bounds":{"minX":-1000,"maxX":-500,"minZ":20500,"maxZ":21000},"roads":[{"id":"571262185","klass":"service","bridge":false,"path":[[-1004.5,20565.5],[-987.7,20563.1]],"mid":[-987.7,20563.1]},{"id":"571262187","klass":"service","bridge":false,"path":[[-1056.1,20616.4],[-971.9,20615.6]],"mid":[-971.9,20615.6]},{"id":"1018182475","klass":"secondary","bridge":false,"path":[[-1000.9,20588.1],[-970.2,20588.1]],"mid":[-970.2,20588.1]},{"id":"1018182476","klass":"service","bridge":false,"path":[[-1004.5,20565.5],[-1012.8,20515],[-996.1,20512.3],[-987.7,20563.1]],"mid":[-996.1,20512.3]},{"id":"5677795","klass":"residential","bridge":false,"path":[[-629.9,20415],[-613.2,20538.2]],"mid":[-613.2,20538.2]},{"id":"221705054","klass":"residential","bridge":false,"path":[[-701.2,20558.7],[-681.1,20699]],"mid":[-681.1,20699]},{"id":"221705057","klass":"residential","bridge":false,"path":[[-791.6,20574],[-789.1,20602.3]],"mid":[-789.1,20602.3]},{"id":"221705058","klass":"residential","bridge":false,"path":[[-525.3,20512.1],[-521.3,20541.5]],"mid":[-521.3,20541.5]},{"id":"568298391","klass":"residential","bridge":false,"path":[[-708,20508.9],[-701.2,20558.7]],"mid":[-701.2,20558.7]},{"id":"568298392","klass":"residential","bridge":false,"path":[[-709.5,20498.4],[-708,20508.9]],"mid":[-708,20508.9]},{"id":"571262188","klass":"service","bridge":false,"path":[[-789.1,20602.3],[-865.2,20609.5]],"mid":[-865.2,20609.5]},{"id":"571262189","klass":"service","bridge":false,"path":[[-627.2,20578.2],[-610.2,20693.4]],"mid":[-610.2,20693.4]},{"id":"586634124","klass":"residential","bridge":false,"path":[[-831.2,20287.4],[-791.6,20574]],"mid":[-791.6,20574]},{"id":"731905595","klass":"service","bridge":false,"path":[[-778,20680.7],[-729.3,20675.3]],"mid":[-729.3,20675.3]},{"id":"731905596","klass":"service","bridge":false,"path":[[-780.2,20664.6],[-771.4,20662.7],[-750,20634.7],[-751.9,20622.8],[-779.3,20603.8],[-789.1,20602.3]],"mid":[-751.9,20622.8]},{"id":"796938245","klass":"service","bridge":false,"path":[[-751.6,20567.6],[-758.6,20523.1],[-739.6,20520.1],[-735.3,20546.6]],"mid":[-739.6,20520.1]},{"id":"854204503","klass":"service","bridge":false,"path":[[-646.5,20580.9],[-659.7,20572],[-667,20576.1],[-668.3,20582.1],[-667.4,20585],[-662.3,20587.3],[-650.7,20585.8],[-646.5,20580.9]],"mid":[-667.4,20585]},{"id":"854204504","klass":"service","bridge":false,"path":[[-646.5,20580.9],[-608,20575.6]],"mid":[-608,20575.6]},{"id":"1017723083","klass":"secondary","bridge":false,"path":[[-746.3,20566.6],[-701.2,20558.7]],"mid":[-701.2,20558.7]},{"id":"1017723084","klass":"secondary","bridge":false,"path":[[-791.6,20574],[-751.6,20567.6]],"mid":[-751.6,20567.6]},{"id":"1018182463","klass":"residential","bridge":false,"path":[[-521.3,20541.5],[-518.6,20561.2]],"mid":[-518.6,20561.2]},{"id":"1018182464","klass":"residential","bridge":false,"path":[[-518.6,20561.2],[-500.2,20695.2]],"mid":[-500.2,20695.2]},{"id":"1018182465","klass":"residential","bridge":false,"path":[[-613.2,20538.2],[-592,20691.9]],"mid":[-592,20691.9]},{"id":"1018182466","klass":"secondary","bridge":false,"path":[[-613.2,20538.2],[-525.3,20512.1]],"mid":[-525.3,20512.1]},{"id":"1018182467","klass":"secondary","bridge":false,"path":[[-701.2,20558.7],[-613.2,20538.2]],"mid":[-613.2,20538.2]},{"id":"1018182468","klass":"secondary","bridge":false,"path":[[-751.6,20567.6],[-746.3,20566.6]],"mid":[-746.3,20566.6]},{"id":"1018182469","klass":"residential","bridge":false,"path":[[-789.1,20602.3],[-780.2,20664.6]],"mid":[-780.2,20664.6]},{"id":"1018182471","klass":"residential","bridge":false,"path":[[-780.2,20664.6],[-778,20680.7]],"mid":[-778,20680.7]},{"id":"1018182472","klass":"residential","bridge":false,"path":[[-778,20680.7],[-779.3,20697]],"mid":[-779.3,20697]},{"id":"1018182473","klass":"secondary","bridge":false,"path":[[-880.3,20583.3],[-829.6,20578.3]],"mid":[-829.6,20578.3]},{"id":"1019873799","klass":"secondary","bridge":false,"path":[[-829.6,20578.3],[-791.6,20574]],"mid":[-791.6,20574]},{"id":"1019873800","klass":"secondary","bridge":false,"path":[[-905.2,20584.7],[-880.3,20583.3]],"mid":[-880.3,20583.3]},{"id":"1331107835","klass":"residential","bridge":false,"path":[[-563.5,20248.4],[-525.3,20512.1]],"mid":[-525.3,20512.1]},{"id":"1495064963","klass":"service","bridge":false,"path":[[-785.3,20629.4],[-760.7,20626]],"mid":[-760.7,20626]},{"id":"5681157","klass":"residential","bridge":false,"path":[[-957.9,20038.4],[-880.3,20583.3]],"mid":[-880.3,20583.3]},{"id":"1018182474","klass":"secondary","bridge":false,"path":[[-970.2,20588.1],[-905.2,20584.7]],"mid":[-905.2,20584.7]},{"id":"1330879407","klass":"service","bridge":false,"path":[[-1044.6,20693.6],[-1030.3,20703.3],[-1011.1,20702.4],[-1002.1,20700.4],[-998.9,20696.2],[-954.9,20690],[-945.6,20679.1],[-876.1,20675.8],[-867.6,20691.2],[-863.2,20693.2],[-832.6,20693.4],[-801.4,20706.5],[-782.7,20702.7],[-779.3,20697]],"mid":[-876.1,20675.8]}],"bridges":[]}