{"tileId":"11_15","bounds":{"minX":5500,"maxX":6000,"minZ":7500,"maxZ":8000},"roads":[{"id":"845696122","klass":"residential","bridge":false,"path":[[4951.9,8005.3],[5674.5,7896],[5700.3,7893.8]],"mid":[5674.5,7896]},{"id":"5682196","klass":"residential","bridge":false,"path":[[6606.9,6838.4],[5789.8,7938.3]],"mid":[5789.8,7938.3]},{"id":"221777100","klass":"primary","bridge":false,"path":[[5158.2,7475.8],[5678.6,7867.2]],"mid":[5678.6,7867.2]},{"id":"263738901","klass":"service","bridge":false,"path":[[5457.8,7969.9],[5660.9,7940.2],[5666.3,7944.1],[5689.8,7940.6]],"mid":[5666.3,7944.1]},{"id":"275300301","klass":"residential","bridge":false,"path":[[5712,7644.4],[5599.1,7795.8]],"mid":[5599.1,7795.8]},{"id":"432554461","klass":"secondary","bridge":false,"path":[[5775.2,7691.9],[5965.2,7834.5]],"mid":[5965.2,7834.5]},{"id":"1144975058","klass":"residential","bridge":false,"path":[[5203.6,7800.7],[5525.7,7753.1]],"mid":[5525.7,7753.1]},{"id":"1495410235","klass":"service","bridge":false,"path":[[5622,7765.1],[5653.5,7788.7]],"mid":[5653.5,7788.7]},{"id":"1000643589","klass":"residential","bridge":false,"path":[[5603,7810.8],[5592.5,7825.1]],"mid":[5592.5,7825.1]},{"id":"1094367902","klass":"residential","bridge":false,"path":[[5599.1,7795.8],[5593.2,7803.7]],"mid":[5593.2,7803.7]},{"id":"1378712812","klass":"residential","bridge":false,"path":[[5620.8,7824.2],[5593.5,7825.1]],"mid":[5593.5,7825.1]},{"id":"5676522","klass":"residential","bridge":false,"path":[[5681.6,7895.3],[5695.1,7975.9]],"mid":[5695.1,7975.9]},{"id":"5682198","klass":"residential","bridge":false,"path":[[5802.6,7960.5],[5774.1,7963.6]],"mid":[5774.1,7963.6]},{"id":"221446581","klass":"primary","bridge":false,"path":[[5894.3,8029.3],[5802.6,7960.5]],"mid":[5802.6,7960.5]},{"id":"765136892","klass":"residential","bridge":false,"path":[[5678.6,7867.2],[5681.6,7895.3]],"mid":[5681.6,7895.3]},{"id":"765136893","klass":"primary","bridge":false,"path":[[5678.6,7867.2],[5722,7897.9],[5802.6,7960.5]],"mid":[5722,7897.9]},{"id":"998905445","klass":"residential","bridge":false,"path":[[5784.4,7947.4],[5774.1,7963.6]],"mid":[5774.1,7963.6]},{"id":"1094362365","klass":"residential","bridge":false,"path":[[5714.3,7892.6],[5725,7890.8]],"mid":[5725,7890.8]},{"id":"1100673845","klass":"residential","bridge":false,"path":[[5774.1,7963.6],[5695.1,7975.9]],"mid":[5695.1,7975.9]},{"id":"1120228234","klass":"residential","bridge":false,"path":[[5700.3,7893.8],[5714.3,7892.6]],"mid":[5714.3,7892.6]},{"id":"1122163038","klass":"residential","bridge":false,"path":[[5789.8,7938.3],[5784.4,7947.4]],"mid":[5784.4,7947.4]},{"id":"1162830447","klass":"residential","bridge":false,"path":[[5847,7994],[5853.1,7985.7]],"mid":[5853.1,7985.7]},{"id":"432554456","klass":"secondary","bridge":false,"path":[[5458.8,7454.4],[5585.4,7549]],"mid":[5585.4,7549]},{"id":"1051012738","klass":"residential","bridge":false,"path":[[5498.7,7756.9],[5510.3,7741.2]],"mid":[5510.3,7741.2]},{"id":"1120233277","klass":"residential","bridge":false,"path":[[5411.5,7650.7],[5522,7502]],"mid":[5522,7502]},{"id":"275300302","klass":"residential","bridge":false,"path":[[5834.1,7480.5],[5712,7644.4]],"mid":[5712,7644.4]},{"id":"221725600","klass":"secondary","bridge":false,"path":[[5585.4,7549],[5775.2,7691.9]],"mid":[5775.2,7691.9]},{"id":"276090454","klass":"residential","bridge":false,"path":[[5700.1,7395.2],[5585.4,7549]],"mid":[5585.4,7549]}],"bridges":[]}