{"tileId":"-1_17","bounds":{"minX":-500,"maxX":0,"minZ":8500,"maxZ":9000},"roads":[{"id":"5679762","klass":"residential","bridge":false,"path":[[1231.9,9571.8],[-195.6,8838.7]],"mid":[-195.6,8838.7]},{"id":"5675809","klass":"residential","bridge":false,"path":[[-596.5,8722.1],[-414.6,8815.4]],"mid":[-414.6,8815.4]},{"id":"5679110","klass":"residential","bridge":false,"path":[[-626.9,8780.3],[-454.2,8879.8]],"mid":[-454.2,8879.8]},{"id":"440498211","klass":"residential","bridge":false,"path":[[-536.4,9008.3],[-494.2,8941.1]],"mid":[-494.2,8941.1]},{"id":"705220928","klass":"service","bridge":false,"path":[[-425,8985.7],[-420,8977.9]],"mid":[-420,8977.9]},{"id":"40416338","klass":"residential","bridge":false,"path":[[-414.6,8815.4],[-345.5,8851]],"mid":[-345.5,8851]},{"id":"123001156","klass":"residential","bridge":false,"path":[[-494.2,8941.1],[-414.6,8815.4],[-341.7,8674.8]],"mid":[-414.6,8815.4]},{"id":"573632388","klass":"residential","bridge":false,"path":[[-454.2,8879.8],[-353.8,8936.6]],"mid":[-353.8,8936.6]},{"id":"686370900","klass":"residential","bridge":false,"path":[[-390.4,9007.9],[-494.2,8941.1]],"mid":[-494.2,8941.1]},{"id":"895615793","klass":"residential","bridge":false,"path":[[-635.8,8345.5],[-269.3,8533.6]],"mid":[-269.3,8533.6]},{"id":"5676712","klass":"residential","bridge":false,"path":[[-273.7,8620.6],[-305.5,8604.3]],"mid":[-305.5,8604.3]},{"id":"5676714","klass":"service","bridge":false,"path":[[-185.7,8666],[-123,8697.3]],"mid":[-123,8697.3]},{"id":"23334088","klass":"secondary","bridge":false,"path":[[-110.7,9058.2],[-68,8993.3]],"mid":[-68,8993.3]},{"id":"25198761","klass":"tertiary","bridge":false,"path":[[-226.8,8733.6],[-159.4,8768.2]],"mid":[-159.4,8768.2]},{"id":"40416342","klass":"residential","bridge":false,"path":[[-159.4,8768.2],[-231.8,8909.5]],"mid":[-231.8,8909.5]},{"id":"40416346","klass":"residential","bridge":false,"path":[[-231.8,8909.5],[-68,8993.3]],"mid":[-68,8993.3]},{"id":"183916201","klass":"residential","bridge":false,"path":[[-269.3,8533.6],[-190.8,8574]],"mid":[-190.8,8574]},{"id":"185196950","klass":"residential","bridge":false,"path":[[78.7,8711.3],[-87,8627.5]],"mid":[-87,8627.5]},{"id":"185196951","klass":"residential","bridge":false,"path":[[-87,8627.5],[-145,8598.1]],"mid":[-145,8598.1]},{"id":"354928473","klass":"residential","bridge":false,"path":[[-87,8627.5],[-159.4,8768.2]],"mid":[-159.4,8768.2]},{"id":"450814751","klass":"tertiary","bridge":false,"path":[[-341.7,8674.8],[-255,8719]],"mid":[-255,8719]},{"id":"551123603","klass":"service","bridge":false,"path":[[8.8,8908.1],[-5.7,8936.4]],"mid":[-5.7,8936.4]},{"id":"573626193","klass":"residential","bridge":false,"path":[[-377.6,8745.1],[-303.5,8784.8]],"mid":[-303.5,8784.8]},{"id":"732577180","klass":"service","bridge":false,"path":[[-161.2,8945.6],[-147.8,8920]],"mid":[-147.8,8920]},{"id":"799512736","klass":"tertiary","bridge":false,"path":[[-246.5,8723.4],[-234.6,8729.6]],"mid":[-234.6,8729.6]},{"id":"821414323","klass":"service","bridge":false,"path":[[-186.6,8932.6],[-216.4,8990.9]],"mid":[-216.4,8990.9]},{"id":"1067447193","klass":"residential","bridge":false,"path":[[-236.3,8639.9],[-273.7,8620.6]],"mid":[-273.7,8620.6]},{"id":"1096967459","klass":"residential","bridge":false,"path":[[-345.5,8851],[-340.1,8853.9]],"mid":[-340.1,8853.9]},{"id":"1096967460","klass":"residential","bridge":false,"path":[[-290.7,8879.1],[-283.8,8882.8]],"mid":[-283.8,8882.8]},{"id":"1133130119","klass":"service","bridge":false,"path":[[-276.5,9001.3],[-287.7,8994.4]],"mid":[-287.7,8994.4]},{"id":"1218520577","klass":"residential","bridge":false,"path":[[-50.8,8556.7],[-87,8627.5]],"mid":[-87,8627.5]},{"id":"1348311434","klass":"residential","bridge":false,"path":[[-283.8,8882.8],[-231.8,8909.5]],"mid":[-231.8,8909.5]}],"bridges":[{"id":"25198757","klass":"tertiary","bridge":true,"path":[[-255,8719],[-246.5,8723.4]],"mid":[-246.5,8723.4]},{"id":"799512735","klass":"tertiary","bridge":true,"path":[[-234.6,8729.6],[-226.8,8733.6]],"mid":[-226.8,8733.6]}]}