{"tileId":"29_1","bounds":{"minX":14500,"maxX":15000,"minZ":500,"maxZ":1000},"roads":[{"id":"5701583","klass":"residential","bridge":false,"path":[[14424.4,1317.6],[14984.4,873.9]],"mid":[14984.4,873.9]},{"id":"5704182","klass":"residential","bridge":false,"path":[[15060.8,-442.9],[14925.9,867.7]],"mid":[14925.9,867.7]},{"id":"5707182","klass":"residential","bridge":false,"path":[[14998.7,-610.8],[14847.3,859.2]],"mid":[14847.3,859.2]},{"id":"5707671","klass":"residential","bridge":false,"path":[[14372.7,1257.9],[14845.6,883.2]],"mid":[14845.6,883.2]},{"id":"5707744","klass":"residential","bridge":false,"path":[[14270.3,1137],[14647,838.5],[14984.4,873.9]],"mid":[14647,838.5]},{"id":"5708238","klass":"residential","bridge":false,"path":[[14432.1,657.6],[14544.2,562.5],[14717.6,580.8]],"mid":[14544.2,562.5]},{"id":"5710066","klass":"residential","bridge":false,"path":[[14904.4,-461.3],[14769.4,851.2]],"mid":[14769.4,851.2]},{"id":"5710187","klass":"residential","bridge":false,"path":[[14293.5,1221.4],[14696.4,900]],"mid":[14696.4,900]},{"id":"276151974","klass":"residential","bridge":false,"path":[[14493.8,847.8],[14525.1,884.7]],"mid":[14525.1,884.7]},{"id":"833984612","klass":"residential","bridge":false,"path":[[14125.9,951],[14284.3,836.2],[14576.1,644.6],[15095.5,698.3]],"mid":[14576.1,644.6]},{"id":"570208782","klass":"service","bridge":false,"path":[[14536.9,541.8],[14510.1,564]],"mid":[14510.1,564]},{"id":"626522570","klass":"residential","bridge":false,"path":[[14845.6,883.2],[14847.3,859.2]],"mid":[14847.3,859.2]},{"id":"626522571","klass":"residential","bridge":false,"path":[[14845.6,883.2],[14873.4,861.9]],"mid":[14873.4,861.9]}],"bridges":[]}