{"tileId":"13_-3","bounds":{"minX":6500,"maxX":7000,"minZ":-1500,"maxZ":-1000},"roads":[{"id":"5709700","klass":"residential","bridge":false,"path":[[6397.2,-1336.8],[6626.5,-1288.5]],"mid":[6626.5,-1288.5]},{"id":"5710459","klass":"residential","bridge":false,"path":[[6431,-1248],[6566.9,-1397.2]],"mid":[6566.9,-1397.2]},{"id":"5710549","klass":"secondary","bridge":false,"path":[[6440,-1172.1],[6522.5,-1155.1]],"mid":[6522.5,-1155.1]},{"id":"772266904","klass":"residential","bridge":false,"path":[[6586.9,-1297.1],[6523.7,-1228.9]],"mid":[6523.7,-1228.9]},{"id":"772266907","klass":"secondary","bridge":false,"path":[[6522.5,-1155.1],[6601.3,-1138.6]],"mid":[6601.3,-1138.6]},{"id":"772266908","klass":"secondary","bridge":false,"path":[[6601.3,-1138.6],[6684.4,-1120.9]],"mid":[6684.4,-1120.9]},{"id":"820272721","klass":"service","bridge":false,"path":[[6552.7,-1148.6],[6551.3,-1140.5],[6558.8,-1124.8]],"mid":[6551.3,-1140.5]},{"id":"820272722","klass":"service","bridge":false,"path":[[6581.8,-1142.5],[6579.3,-1129.6]],"mid":[6579.3,-1129.6]},{"id":"820272723","klass":"service","bridge":false,"path":[[6579.3,-1129.6],[6595,-1121.5]],"mid":[6595,-1121.5]},{"id":"820272724","klass":"service","bridge":false,"path":[[6558.8,-1124.8],[6586.9,-1108.2]],"mid":[6586.9,-1108.2]},{"id":"956743202","klass":"residential","bridge":false,"path":[[6627.6,-1340.7],[6586.9,-1297.1]],"mid":[6586.9,-1297.1]},{"id":"1314896796","klass":"residential","bridge":false,"path":[[6602.3,-1143.5],[6601.3,-1138.6]],"mid":[6601.3,-1138.6]},{"id":"1479963584","klass":"motorway","bridge":false,"path":[[6534.6,-1191.2],[6611.7,-1174]],"mid":[6611.7,-1174]},{"id":"122738248","klass":"motorway","bridge":false,"path":[[7423.6,-995.7],[7292.9,-1020],[6836.5,-1116.3],[6777.9,-1132.2],[6698.7,-1161.6],[6597.6,-1194.2]],"mid":[6777.9,-1132.2]},{"id":"1433505939","klass":"motorway","bridge":false,"path":[[6794,-1145.8],[6773.3,-1160.2],[6752.2,-1169.1],[6695.1,-1173.6],[6622.2,-1191],[6597.6,-1194.2]],"mid":[6695.1,-1173.6]}],"bridges":[{"id":"46738922","klass":"residential","bridge":true,"path":[[6615,-1203.3],[6602.3,-1143.5]],"mid":[6602.3,-1143.5]}]}