{"tileId":"13_-1","bounds":{"minX":6500,"maxX":7000,"minZ":-500,"maxZ":0},"roads":[{"id":"5702719","klass":"residential","bridge":false,"path":[[6044,-832.1],[6644.1,-460.9],[6735.2,-407.4]],"mid":[6644.1,-460.9]},{"id":"387038662","klass":"residential","bridge":false,"path":[[5935.2,-655.9],[6413.5,-359.3],[6549,-278.2],[6658.1,-208.2],[6666.4,-205.3]],"mid":[6549,-278.2]},{"id":"198595464","klass":"residential","bridge":false,"path":[[6582.8,-36.6],[6560.3,-10.8],[6501.6,88.3]],"mid":[6560.3,-10.8]},{"id":"198595465","klass":"residential","bridge":false,"path":[[6666.4,-205.3],[6634.7,-128.9]],"mid":[6634.7,-128.9]},{"id":"198595550","klass":"residential","bridge":false,"path":[[6666.4,-205.3],[6741.4,-178.4]],"mid":[6741.4,-178.4]},{"id":"820306781","klass":"service","bridge":false,"path":[[6721.1,-34.8],[6713,-16.2]],"mid":[6713,-16.2]},{"id":"820408834","klass":"residential","bridge":false,"path":[[6634.7,-128.9],[6622,-102.7],[6582.8,-36.6]],"mid":[6622,-102.7]},{"id":"5710640","klass":"residential","bridge":false,"path":[[6789.7,82.6],[6812.5,-159.3]],"mid":[6812.5,-159.3]},{"id":"820531727","klass":"service","bridge":false,"path":[[6937.9,-118.1],[6975.5,-122.8]],"mid":[6975.5,-122.8]},{"id":"1495773145","klass":"service","bridge":false,"path":[[6936.7,-126.4],[6875.5,-117.5],[6873,-121],[6873.4,-142.6]],"mid":[6873,-121]},{"id":"5705225","klass":"residential","bridge":false,"path":[[6735.2,-407.4],[6728.9,-396.7],[6666.4,-205.3]],"mid":[6728.9,-396.7]},{"id":"5708341","klass":"residential","bridge":false,"path":[[6801.1,-366.3],[6741.4,-178.4]],"mid":[6741.4,-178.4]},{"id":"658605999","klass":"residential","bridge":false,"path":[[6735.2,-407.4],[6822,-353.3]],"mid":[6822,-353.3]},{"id":"820306760","klass":"service","bridge":false,"path":[[6789.4,-169.4],[6794.4,-179.4],[6826.5,-293.1]],"mid":[6794.4,-179.4]},{"id":"820306761","klass":"residential","bridge":false,"path":[[6741.4,-178.4],[6805.6,-167.2],[6812.5,-159.3]],"mid":[6805.6,-167.2]},{"id":"820306770","klass":"service","bridge":false,"path":[[6714.6,-19.5],[6798.9,-10.7]],"mid":[6798.9,-10.7]},{"id":"351259048","klass":"service","bridge":false,"path":[[6721,-574.5],[6753.3,-554.9],[6718.8,-498.9],[6686.6,-518.6]],"mid":[6718.8,-498.9]},{"id":"625350108","klass":"service","bridge":false,"path":[[6495,-356.4],[6561.9,-316.2]],"mid":[6561.9,-316.2]},{"id":"625350109","klass":"service","bridge":false,"path":[[6529.6,-335.6],[6592.6,-440.7]],"mid":[6592.6,-440.7]},{"id":"625350110","klass":"service","bridge":false,"path":[[6559.3,-461.1],[6625.8,-419.9]],"mid":[6625.8,-419.9]},{"id":"1495785630","klass":"service","bridge":false,"path":[[6527.6,-409.4],[6561.9,-389.5]],"mid":[6561.9,-389.5]},{"id":"216931921","klass":"tertiary","bridge":false,"path":[[7012.3,-295.1],[6992.6,-258.5]],"mid":[6992.6,-258.5]},{"id":"820302330","klass":"service","bridge":false,"path":[[7028.4,-342.5],[6996.2,-329.8],[6990.1,-341.6],[7026.2,-356.7]],"mid":[6990.1,-341.6]},{"id":"1013707292","klass":"service","bridge":false,"path":[[6980,-337.3],[6990.1,-341.6]],"mid":[6990.1,-341.6]}],"bridges":[]}