{"tileId":"37_1","bounds":{"minX":18500,"maxX":19000,"minZ":500,"maxZ":1000},"roads":[{"id":"5703543","klass":"tertiary","bridge":false,"path":[[18349.8,900.9],[18363.9,901.3],[18720.3,772.1],[18766.9,744],[18793.1,725.1]],"mid":[18720.3,772.1]},{"id":"620313416","klass":"tertiary","bridge":false,"path":[[18793.1,725.1],[18762.3,733],[18715.8,762.1],[18360.7,890.3],[18349.8,900.9]],"mid":[18715.8,762.1]},{"id":"5699885","klass":"residential","bridge":false,"path":[[18744.4,618.2],[18967.5,537.1]],"mid":[18967.5,537.1]},{"id":"5705879","klass":"residential","bridge":false,"path":[[18928.9,1102.7],[18861.5,916]],"mid":[18861.5,916]},{"id":"531039149","klass":"tertiary","bridge":false,"path":[[18856,1134.4],[18731.9,764],[18710.3,713.7],[18672,660.9],[18644.4,631],[18540.7,550.3],[18514.7,522.3],[18471.6,469.8],[18436.4,405.3],[18390.9,270.7],[18381.9,261.2]],"mid":[18540.7,550.3]},{"id":"552256531","klass":"residential","bridge":false,"path":[[19166.5,804.5],[18861.5,916]],"mid":[18861.5,916]},{"id":"844872702","klass":"residential","bridge":false,"path":[[18650,480.9],[18665.2,618.4]],"mid":[18665.2,618.4]},{"id":"1419079088","klass":"residential","bridge":false,"path":[[18695.8,200.4],[18744.4,618.2]],"mid":[18744.4,618.2]},{"id":"5707078","klass":"residential","bridge":false,"path":[[18782.3,686.1],[18864.6,682.4]],"mid":[18864.6,682.4]},{"id":"219973374","klass":"tertiary","bridge":false,"path":[[18615.4,626.2],[18648,655],[18670.8,681.8],[18696.2,718.8],[18720.3,772.1],[18850,1151.9]],"mid":[18696.2,718.8]},{"id":"250029625","klass":"tertiary","bridge":false,"path":[[18782.3,686.1],[18824.6,707.7]],"mid":[18824.6,707.7]},{"id":"531039152","klass":"residential","bridge":false,"path":[[18592.8,637.4],[18615.4,626.2]],"mid":[18615.4,626.2]},{"id":"552256530","klass":"residential","bridge":false,"path":[[18861.5,916],[18793.1,725.1]],"mid":[18793.1,725.1]},{"id":"574771971","klass":"tertiary","bridge":false,"path":[[18668.7,633.7],[18644.4,631]],"mid":[18644.4,631]},{"id":"620313417","klass":"tertiary","bridge":false,"path":[[18824.6,707.7],[18864.6,682.4]],"mid":[18864.6,682.4]},{"id":"844872703","klass":"residential","bridge":false,"path":[[18594.4,494.5],[18600.6,503]],"mid":[18600.6,503]},{"id":"844872704","klass":"residential","bridge":false,"path":[[18585.9,618.6],[18582.1,608.9]],"mid":[18582.1,608.9]},{"id":"1370405680","klass":"tertiary","bridge":false,"path":[[18793.1,725.1],[18824.6,707.7]],"mid":[18824.6,707.7]},{"id":"1416500603","klass":"tertiary","bridge":false,"path":[[18518.9,642.1],[18585.9,618.6]],"mid":[18585.9,618.6]},{"id":"1416500604","klass":"tertiary","bridge":false,"path":[[18605.1,599.5],[18516.1,632.8]],"mid":[18516.1,632.8]},{"id":"1416500605","klass":"residential","bridge":false,"path":[[18674.4,641.1],[18751.5,673.3]],"mid":[18751.5,673.3]},{"id":"1416500606","klass":"residential","bridge":false,"path":[[18744.4,618.2],[18751.5,673.3]],"mid":[18751.5,673.3]},{"id":"1416504697","klass":"tertiary","bridge":false,"path":[[18516.1,632.8],[18509.1,635.3]],"mid":[18509.1,635.3]},{"id":"1416504698","klass":"tertiary","bridge":false,"path":[[18512.3,644.3],[18518.9,642.1]],"mid":[18518.9,642.1]},{"id":"1416512270","klass":"residential","bridge":false,"path":[[18585.9,618.6],[18621.1,722.4]],"mid":[18621.1,722.4]},{"id":"1416512271","klass":"residential","bridge":false,"path":[[18665.2,618.4],[18668.7,633.7]],"mid":[18668.7,633.7]},{"id":"1416512272","klass":"residential","bridge":false,"path":[[18668.7,633.7],[18674.4,641.1]],"mid":[18674.4,641.1]},{"id":"1416512273","klass":"tertiary","bridge":false,"path":[[18648,655],[18674.4,641.1]],"mid":[18674.4,641.1]},{"id":"1416665631","klass":"tertiary","bridge":false,"path":[[18589.3,606.2],[18615.4,626.2]],"mid":[18615.4,626.2]},{"id":"1419083531","klass":"residential","bridge":false,"path":[[18751.5,673.3],[18782.3,686.1]],"mid":[18782.3,686.1]},{"id":"1419102215","klass":"residential","bridge":false,"path":[[18621.1,722.4],[18643.3,788.4]],"mid":[18643.3,788.4]},{"id":"1419893725","klass":"tertiary","bridge":false,"path":[[18585.9,618.6],[18598.1,613.1],[18605.1,599.5]],"mid":[18598.1,613.1]},{"id":"1419894556","klass":"residential","bridge":false,"path":[[18472.8,532.9],[18503.1,618.3]],"mid":[18503.1,618.3]},{"id":"1419894557","klass":"residential","bridge":false,"path":[[18503.1,618.3],[18569,815.5]],"mid":[18569,815.5]},{"id":"1419933741","klass":"residential","bridge":false,"path":[[18508.4,535.8],[18522.5,530.7]],"mid":[18522.5,530.7]},{"id":"5703706","klass":"residential","bridge":false,"path":[[19066.1,1016.8],[18938.7,660.7]],"mid":[18938.7,660.7]}],"bridges":[]}