{"tileId":"6_-12","bounds":{"minX":3000,"maxX":3500,"minZ":-6000,"maxZ":-5500},"roads":[{"id":"5670742","klass":"residential","bridge":false,"path":[[3425.9,-5310.9],[3042.9,-5523.7]],"mid":[3042.9,-5523.7]},{"id":"46594127","klass":"residential","bridge":false,"path":[[3441.8,-5679.8],[3202.2,-5813]],"mid":[3202.2,-5813]},{"id":"165473831","klass":"primary","bridge":false,"path":[[3317.1,-6020.7],[3262.6,-5921.4]],"mid":[3262.6,-5921.4]},{"id":"275298543","klass":"residential","bridge":false,"path":[[3292,-5943.8],[3279.1,-5951]],"mid":[3279.1,-5951]},{"id":"305323030","klass":"primary","bridge":false,"path":[[3374.7,-5528.8],[3361.4,-5535.9]],"mid":[3361.4,-5535.9]},{"id":"305323035","klass":"primary","bridge":false,"path":[[3361.4,-5535.9],[3182.9,-5635.4]],"mid":[3182.9,-5635.4]},{"id":"332388684","klass":"primary","bridge":false,"path":[[3425.5,-5500.4],[3374.7,-5528.8]],"mid":[3374.7,-5528.8]},{"id":"420877067","klass":"primary","bridge":false,"path":[[3112.5,-5618.7],[3136.1,-5661.4]],"mid":[3136.1,-5661.4]},{"id":"420877071","klass":"primary","bridge":false,"path":[[3270.7,-5904.9],[3292,-5943.8]],"mid":[3292,-5943.8]},{"id":"420877072","klass":"primary","bridge":false,"path":[[3136.1,-5661.4],[3154.5,-5695.8]],"mid":[3154.5,-5695.8]},{"id":"420877078","klass":"primary","bridge":false,"path":[[3104.5,-5635.3],[3081.2,-5593.5]],"mid":[3081.2,-5593.5]},{"id":"420877081","klass":"primary","bridge":false,"path":[[3193.9,-5765.4],[3216,-5805.2]],"mid":[3216,-5805.2]},{"id":"420877082","klass":"primary","bridge":false,"path":[[3123,-5668.7],[3104.5,-5635.3]],"mid":[3104.5,-5635.3]},{"id":"420877090","klass":"primary","bridge":false,"path":[[3146.5,-5712],[3123,-5668.7]],"mid":[3123,-5668.7]},{"id":"420877091","klass":"primary","bridge":false,"path":[[3035.5,-5479.1],[3056.2,-5516.3]],"mid":[3056.2,-5516.3]},{"id":"420877093","klass":"primary","bridge":false,"path":[[3154.5,-5695.8],[3176.7,-5736.4]],"mid":[3176.7,-5736.4]},{"id":"420877096","klass":"primary","bridge":false,"path":[[3216,-5805.2],[3270.7,-5904.9]],"mid":[3270.7,-5904.9]},{"id":"420877103","klass":"primary","bridge":false,"path":[[3081.2,-5593.5],[3042.9,-5523.7]],"mid":[3042.9,-5523.7]},{"id":"420877104","klass":"primary","bridge":false,"path":[[3056.2,-5516.3],[3102.1,-5599.8]],"mid":[3102.1,-5599.8]},{"id":"420878091","klass":"secondary","bridge":false,"path":[[3387.5,-5582.6],[3361.4,-5535.9]],"mid":[3361.4,-5535.9]},{"id":"420878093","klass":"secondary","bridge":false,"path":[[3374.7,-5528.8],[3405.3,-5584.2]],"mid":[3405.3,-5584.2]},{"id":"420878094","klass":"secondary","bridge":false,"path":[[3405.3,-5584.2],[3415.7,-5603.5]],"mid":[3415.7,-5603.5]},{"id":"421506980","klass":"secondary","bridge":false,"path":[[3353.9,-5490.8],[3374.7,-5528.8]],"mid":[3374.7,-5528.8]},{"id":"497264363","klass":"secondary","bridge":false,"path":[[3403,-5610.4],[3387.5,-5582.6]],"mid":[3387.5,-5582.6]},{"id":"497264364","klass":"secondary","bridge":false,"path":[[3441.8,-5679.8],[3403,-5610.4]],"mid":[3403,-5610.4]},{"id":"497264365","klass":"residential","bridge":false,"path":[[3454.5,-5672.5],[3441.8,-5679.8]],"mid":[3441.8,-5679.8]},{"id":"497264367","klass":"secondary","bridge":false,"path":[[3415.7,-5603.5],[3454.5,-5672.5]],"mid":[3454.5,-5672.5]},{"id":"570158865","klass":"service","bridge":false,"path":[[3171.7,-5830.2],[3185.8,-5856.2]],"mid":[3185.8,-5856.2]},{"id":"570158870","klass":"service","bridge":false,"path":[[3198.8,-5996.2],[3184.4,-5968.2]],"mid":[3184.4,-5968.2]},{"id":"664893484","klass":"primary","bridge":false,"path":[[3240.6,-5882],[3146.5,-5712]],"mid":[3146.5,-5712]},{"id":"962623445","klass":"primary","bridge":false,"path":[[3262.6,-5921.4],[3240.6,-5882]],"mid":[3240.6,-5882]},{"id":"968806228","klass":"primary","bridge":false,"path":[[3176.7,-5736.4],[3185.1,-5751]],"mid":[3185.1,-5751]},{"id":"1046751100","klass":"residential","bridge":false,"path":[[3453.7,-5582.3],[3415.7,-5603.5]],"mid":[3415.7,-5603.5]},{"id":"1053621930","klass":"primary","bridge":false,"path":[[3185.1,-5751],[3193.9,-5765.4]],"mid":[3193.9,-5765.4]},{"id":"1053641173","klass":"primary","bridge":false,"path":[[3102.1,-5599.8],[3112.5,-5618.7]],"mid":[3112.5,-5618.7]},{"id":"1321780272","klass":"primary","bridge":false,"path":[[3156.2,-5650.3],[3136.1,-5661.4]],"mid":[3136.1,-5661.4]},{"id":"1321780273","klass":"primary","bridge":false,"path":[[3182.9,-5635.4],[3156.2,-5650.3]],"mid":[3156.2,-5650.3]},{"id":"1321780274","klass":"primary","bridge":false,"path":[[3136.1,-5661.4],[3123,-5668.7]],"mid":[3123,-5668.7]},{"id":"1495840981","klass":"service","bridge":false,"path":[[3287.2,-5674.9],[3281.1,-5663.6]],"mid":[3281.1,-5663.6]},{"id":"1495840982","klass":"service","bridge":false,"path":[[3279.7,-5679.1],[3273.5,-5667.8]],"mid":[3273.5,-5667.8]},{"id":"420878077","klass":"secondary","bridge":false,"path":[[3496.1,-5778.9],[3479.8,-5748.9]],"mid":[3479.8,-5748.9]},{"id":"1032468213","klass":"secondary","bridge":false,"path":[[3517.6,-5818.8],[3496.1,-5778.9]],"mid":[3496.1,-5778.9]},{"id":"46594129","klass":"residential","bridge":false,"path":[[3681.4,-5455.7],[3453.7,-5582.3]],"mid":[3453.7,-5582.3]},{"id":"275298544","klass":"residential","bridge":false,"path":[[3517.6,-5818.8],[3292,-5943.8]],"mid":[3292,-5943.8]},{"id":"332388685","klass":"primary","bridge":false,"path":[[3472.5,-5474.3],[3425.5,-5500.4]],"mid":[3425.5,-5500.4]},{"id":"420878117","klass":"secondary","bridge":false,"path":[[3479.8,-5748.9],[3441.8,-5679.8]],"mid":[3441.8,-5679.8]},{"id":"497264366","klass":"residential","bridge":false,"path":[[3720,-5524.9],[3454.5,-5672.5]],"mid":[3454.5,-5672.5]}],"bridges":[]}