{"tileId":"-1_11","bounds":{"minX":-500,"maxX":0,"minZ":5500,"maxZ":6000},"roads":[{"id":"5676833","klass":"residential","bridge":false,"path":[[-169.4,5950.9],[-247.4,5948.7]],"mid":[-247.4,5948.7]},{"id":"227064538","klass":"residential","bridge":false,"path":[[-96.6,6100.8],[-89.9,5954.9]],"mid":[-89.9,5954.9]},{"id":"440633419","klass":"residential","bridge":false,"path":[[-89.9,5954.9],[-169.4,5950.9]],"mid":[-169.4,5950.9]},{"id":"440633423","klass":"residential","bridge":false,"path":[[77.2,5963.2],[-89.9,5954.9]],"mid":[-89.9,5954.9]}],"bridges":[]}